swanhub/__init__.py
swanhub/__main__.py
swanhub/_version.py
swanhub/app.py
swanhub/error_handler.py
swanhub/handlers_configs.py
swanhub/spawn_handler.py
swanhub/userapi_handler.py
swanhub/templates/404.html
swanhub/templates/home.html
swanhub/templates/login.html
swanhub/templates/maintenance.html
swanhub/templates/not_running.html
swanhub/templates/page.html
swanhub/templates/spawn.html
swanhub/templates/spawn_conflict.html
swanhub/templates/spawn_pending.html
swanhub/templates/stop_pending.html
swanhub/templates/unreachable_container.html
swanhub-1.0.8.dist-info/METADATA
swanhub-1.0.8.dist-info/WHEEL
swanhub-1.0.8.dist-info/entry_points.txt
swanhub-1.0.8.dist-info/top_level.txt
swanhub-1.0.8.dist-info/RECORD
